RsCmwLteMeas/RsCmwLteMeas.py
RsCmwLteMeas/__init__.py
RsCmwLteMeas/enums.py
RsCmwLteMeas/py.typed.py
RsCmwLteMeas/repcap.py
RsCmwLteMeas/CustomFiles/__init__.py
RsCmwLteMeas/CustomFiles/events.py
RsCmwLteMeas/CustomFiles/reliability.py
RsCmwLteMeas/CustomFiles/utilities.py
RsCmwLteMeas/Implementations/__init__.py
RsCmwLteMeas/Implementations/Configure/Emtc.py
RsCmwLteMeas/Implementations/Configure/Network.py
RsCmwLteMeas/Implementations/Configure/Pcc.py
RsCmwLteMeas/Implementations/Configure/__init__.py
RsCmwLteMeas/Implementations/Configure/CarrierAggregation/ChannelBw.py
RsCmwLteMeas/Implementations/Configure/CarrierAggregation/Mcarrier.py
RsCmwLteMeas/Implementations/Configure/CarrierAggregation/Mode.py
RsCmwLteMeas/Implementations/Configure/CarrierAggregation/__init__.py
RsCmwLteMeas/Implementations/Configure/CarrierAggregation/Frequency/Aggregated.py
RsCmwLteMeas/Implementations/Configure/CarrierAggregation/Frequency/__init__.py
RsCmwLteMeas/Implementations/Configure/CarrierAggregation/Maping/Scc.py
RsCmwLteMeas/Implementations/Configure/CarrierAggregation/Maping/__init__.py
RsCmwLteMeas/Implementations/Configure/CarrierAggregation/Scc/AcSpacing.py
RsCmwLteMeas/Implementations/Configure/CarrierAggregation/Scc/__init__.py
RsCmwLteMeas/Implementations/Configure/Cc/ChannelBw.py
RsCmwLteMeas/Implementations/Configure/Cc/__init__.py
RsCmwLteMeas/Implementations/Configure/MultiEval/MsubFrames.py
RsCmwLteMeas/Implementations/Configure/MultiEval/NsValue.py
RsCmwLteMeas/Implementations/Configure/MultiEval/Pcc.py
RsCmwLteMeas/Implementations/Configure/MultiEval/Power.py
RsCmwLteMeas/Implementations/Configure/MultiEval/Srs.py
RsCmwLteMeas/Implementations/Configure/MultiEval/Tmode.py
RsCmwLteMeas/Implementations/Configure/MultiEval/__init__.py
RsCmwLteMeas/Implementations/Configure/MultiEval/Bler/Sframes.py
RsCmwLteMeas/Implementations/Configure/MultiEval/Bler/__init__.py
RsCmwLteMeas/Implementations/Configure/MultiEval/Cc/PlcId.py
rscmwltemeas-4.0.231.dist-info/METADATA
rscmwltemeas-4.0.231.dist-info/WHEEL
rscmwltemeas-4.0.231.dist-info/top_level.txt
rscmwltemeas-4.0.231.dist-info/RECORD
