Metadata-Version: 2.4
Name: RsCmwLteMeas
Version: 4.0.231
Summary: CMW LTE Measurement Remote-control module
Author: Rohde & Schwarz GmbH & Co. KG
Maintainer: Rohde & Schwarz GmbH & Co. KG
License-Expression: MIT
Project-URL: Documentation, https://RsCmwLteMeas.readthedocs.io/
Project-URL: Examples, https://github.com/Rohde-Schwarz/Examples/
Keywords: CMW,CMP,CMW500,CMW100
Classifier: Development Status :: 5 - Production/Stable
Classifier: Topic :: Scientific/Engineering :: Instrument Drivers
Classifier: Programming Language :: Python :: 3
Classifier: Programming Language :: Python :: 3.9
Classifier: Programming Language :: Python :: 3.10
Classifier: Programming Language :: Python :: 3.11
Classifier: Programming Language :: Python :: 3.12
Classifier: Programming Language :: Python :: 3.13
Requires-Python: >=3.9
Requires-Dist: pyvisa>=1.13.0
Requires-Dist: typing-extensions>=4.0.0
